smartratelimit/__init__.py
smartratelimit/async_client.py
smartratelimit/cli.py
smartratelimit/core.py
smartratelimit/detector.py
smartratelimit/metrics.py
smartratelimit/models.py
smartratelimit/retry.py
smartratelimit/storage.py
smartratelimit-0.3.1.dist-info/licenses/LICENSE
smartratelimit-0.3.1.dist-info/METADATA
smartratelimit-0.3.1.dist-info/WHEEL
smartratelimit-0.3.1.dist-info/entry_points.txt
smartratelimit-0.3.1.dist-info/top_level.txt
smartratelimit-0.3.1.dist-info/RECORD
