Metadata-Version: 2.4
Name: smartratelimit
Version: 0.3.1
Summary: A Python library that automatically manages API rate limits, preventing 429 errors
Author-email: Olumide Ola <olumide@olaverse.co.uk>
License: MIT
Project-URL: Homepage, https://github.com/olastephen/smartratelimit
Project-URL: Documentation, https://github.com/olastephen/smartratelimit#readme
Project-URL: Repository, https://github.com/olastephen/smartratelimit
Project-URL: Issues, https://github.com/olastephen/smartratelimit/issues
Keywords: rate-limit,api,429,throttling,requests
Classifier: Development Status :: 4 - Beta
Classifier: Intended Audience :: Developers
Classifier: License :: OSI Approved :: MIT License
Classifier: Programming Language :: Python :: 3
Classifier: Programming Language :: Python :: 3.8
Classifier: Programming Language :: Python :: 3.9
Classifier: Programming Language :: Python :: 3.10
Classifier: Programming Language :: Python :: 3.11
Classifier: Programming Language :: Python :: 3.12
Classifier: Topic :: Software Development :: Libraries :: Python Modules
Classifier: Topic :: Internet :: WWW/HTTP
Requires-Python: >=3.8
License-File: LICENSE
Requires-Dist: requests>=2.25.0
Provides-Extra: redis
Requires-Dist: redis>=4.0.0; extra == "redis"
Provides-Extra: httpx
Requires-Dist: httpx>=0.24.0; extra == "httpx"
Provides-Extra: aiohttp
Requires-Dist: aiohttp>=3.8.0; extra == "aiohttp"
Provides-Extra: all
Requires-Dist: redis>=4.0.0; extra == "all"
Requires-Dist: httpx>=0.24.0; extra == "all"
Requires-Dist: aiohttp>=3.8.0; extra == "all"
Dynamic: license-file
